README.md
setup.py
michael_tools/__init__.py
michael_tools.egg-info/PKG-INFO
michael_tools.egg-info/SOURCES.txt
michael_tools.egg-info/dependency_links.txt
michael_tools.egg-info/requires.txt
michael_tools.egg-info/top_level.txt
michael_tools/excel_op/__init__.py
michael_tools/excel_op/excel_op.py
michael_tools/file_op/__init__.py
michael_tools/file_op/create_file.py
michael_tools/file_op/delete_file.py
michael_tools/file_op/dir_op.py
michael_tools/file_op/read_file.py
michael_tools/file_op/unique_filepath.py
michael_tools/file_op/write_file.py
michael_tools/json_op/__init__.py
michael_tools/json_op/json_op.py
michael_tools/openapi_op/__init__.py
michael_tools/openapi_op/call_model.py
michael_tools/openapi_op/multi_chat.py
michael_tools/sql_op/__init__.py
michael_tools/sql_op/connect_db.py
michael_tools/time_op/__init__.py
michael_tools/time_op/time_op.py
michael_tools/txt_operation/__init__.py
michael_tools/txt_operation/remove_trailing_newline.py