Metadata-Version: 2.4
Name: michael_tools
Version: 0.1.3
Summary: This is my personal toolkit
Author: Michael Smith
Author-email: 1422749310@qq.com
Classifier: Programming Language :: Python :: 3
Classifier: Operating System :: Unix
Classifier: Operating System :: MacOS :: MacOS X
Classifier: Operating System :: Microsoft :: Windows
Requires-Python: >=3.13
Requires-Dist: openpyxl
Requires-Dist: pandas
Requires-Dist: pymysql
Requires-Dist: openai
Dynamic: author
Dynamic: author-email
Dynamic: classifier
Dynamic: description
Dynamic: description-content-type
Dynamic: requires-dist
Dynamic: requires-python
Dynamic: summary
